setup.py
provoke/__init__.py
provoke/amqp.py
provoke/app.py
provoke/config.py
provoke/connectionpool.py
provoke/http.py
provoke/mysql.py
provoke.egg-info/PKG-INFO
provoke.egg-info/SOURCES.txt
provoke.egg-info/dependency_links.txt
provoke.egg-info/entry_points.txt
provoke.egg-info/pbr.json
provoke.egg-info/requires.txt
provoke.egg-info/top_level.txt
provoke/example/__init__.py
provoke/example/client.py
provoke/example/worker.py
provoke/worker/__init__.py
provoke/worker/main.py
provoke/worker/system.py
test/test_amqp.py
test/test_app.py
test/test_config.py
test/test_connectionpool.py
test/test_http.py
test/test_mysql.py
test/test_worker.py