Metadata-Version: 1.0
Name: provoke
Version: 0.4.1
Summary: Lightweight, asynchronous function execution in Python using AMQP.
Home-page: UNKNOWN
Author: Ian Good
Author-email: icgood@gmail.com
License: UNKNOWN
Platform: UNKNOWN
